zosjcl/__init__.py
zosjcl/zosjcl.py
zosjcl-0.0.1.dist-info/LICENSE
zosjcl-0.0.1.dist-info/METADATA
zosjcl-0.0.1.dist-info/WHEEL
zosjcl-0.0.1.dist-info/top_level.txt
zosjcl-0.0.1.dist-info/RECORD
